coax/__about__.py
coax/__init__.py
coax/exceptions.py
coax/features.py
coax/interface.py
coax/multiplexer.py
coax/parity.py
coax/protocol.py
coax/serial_interface.py
pycoax-0.11.2.dist-info/LICENSE
pycoax-0.11.2.dist-info/METADATA
pycoax-0.11.2.dist-info/WHEEL
pycoax-0.11.2.dist-info/top_level.txt
pycoax-0.11.2.dist-info/RECORD
