Metadata-Version: 2.1
Name: pycoax
Version: 0.11.2
Summary: IBM 3270 coaxial interface
Home-page: https://github.com/lowobservable/coax
Author: Andrew Kay
Author-email: projects@ajk.me
Classifier: Development Status :: 3 - Alpha
Classifier: License :: OSI Approved :: ISC License (ISCL)
Classifier: Operating System :: OS Independent
Classifier: Programming Language :: Python :: 3
Classifier: Topic :: Communications
Classifier: Topic :: Terminals
License-File: LICENSE
Requires-Dist: pyserial (==3.5)
Requires-Dist: sliplib (==0.6.2)
